xia_project_iaas/__init__.py
xia_project_iaas/billing.cp39-win_amd64.pyd
xia_project_iaas/project.cp39-win_amd64.pyd
xia_project_iaas-0.0.1.dist-info/LICENSE.txt
xia_project_iaas-0.0.1.dist-info/METADATA
xia_project_iaas-0.0.1.dist-info/WHEEL
xia_project_iaas-0.0.1.dist-info/top_level.txt
xia_project_iaas-0.0.1.dist-info/RECORD
